megalodon/__init__.py
megalodon/__main__.py
megalodon/aggregate.py
megalodon/backends.py
megalodon/banding.py
megalodon/calibration.py
megalodon/constrained_decoding.py
megalodon/decode.cpython-37m-darwin.so
megalodon/fast5_io.py
megalodon/logging.py
megalodon/mapping.py
megalodon/megalodon.py
megalodon/megalodon_helper.py
megalodon/megalodon_multiprocessing.py
megalodon/mods.py
megalodon/signal_mapping.py
megalodon/validation.py
megalodon/variants.py
megalodon/model_data/dna_r10.3_450bps_fast.cfg/megalodon_variant_calibration.npz
megalodon/model_data/dna_r10.3_450bps_fast_prom.cfg/megalodon_variant_calibration.npz
megalodon/model_data/dna_r10.3_450bps_hac.cfg/megalodon_variant_calibration.npz
megalodon/model_data/dna_r10.3_450bps_hac_prom.cfg/megalodon_variant_calibration.npz
megalodon/model_data/dna_r10.3_450bps_modbases_5mc_hac_prom.cfg/megalodon_mod_calibration.npz
megalodon/model_data/dna_r10.3_450bps_modbases_5mc_hac_prom.cfg/megalodon_variant_calibration.npz
megalodon/model_data/dna_r9.4.1_450bps_fast.cfg/megalodon_variant_calibration.npz
megalodon/model_data/dna_r9.4.1_450bps_fast_prom.cfg/megalodon_variant_calibration.npz
megalodon/model_data/dna_r9.4.1_450bps_hac.cfg/megalodon_variant_calibration.npz
megalodon/model_data/dna_r9.4.1_450bps_hac_prom.cfg/megalodon_variant_calibration.npz
megalodon/model_data/dna_r9.4.1_450bps_modbases_5mc_hac.cfg/megalodon_mod_calibration.npz
megalodon/model_data/dna_r9.4.1_450bps_modbases_5mc_hac.cfg/megalodon_variant_calibration.npz
megalodon/model_data/dna_r9.4.1_450bps_modbases_5mc_hac_prom.cfg/megalodon_mod_calibration.npz
megalodon/model_data/dna_r9.4.1_450bps_modbases_5mc_hac_prom.cfg/megalodon_variant_calibration.npz
megalodon/model_data/dna_r9.4.1_450bps_modbases_dam-dcm-cpg_hac.cfg/megalodon_mod_calibration.npz
megalodon/model_data/dna_r9.4.1_450bps_modbases_dam-dcm-cpg_hac.cfg/megalodon_variant_calibration.npz
megalodon/model_data/dna_r9.4.1_450bps_modbases_dam-dcm-cpg_hac_prom.cfg/megalodon_mod_calibration.npz
megalodon-2.5.0.dist-info/LICENCE.txt
megalodon-2.5.0.dist-info/METADATA
megalodon-2.5.0.dist-info/WHEEL
megalodon-2.5.0.dist-info/entry_points.txt
megalodon-2.5.0.dist-info/top_level.txt
megalodon-2.5.0.dist-info/RECORD
