Metadata-Version: 2.1
Name: megalodon
Version: 2.5.0
Summary: Nanopore base calling augmentation.
Home-page: https://github.com/nanoporetech/megalodon
Author: Marcus Stoiber
Maintainer: Marcus Stoiber
Maintainer-email: marcus.stoiber@nanoporetech.com
License: ont_public_licence
Platform: any
Classifier: Development Status :: 4 - Beta
Classifier: Environment :: Console
Classifier: Environment :: GPU
Classifier: Intended Audience :: Developers
Classifier: Intended Audience :: Science/Research
Classifier: License :: OSI Approved :: Mozilla Public License 2.0 (MPL 2.0)
Classifier: Natural Language :: English
Classifier: Operating System :: Unix
Classifier: Programming Language :: Python :: 3 :: Only
Classifier: Topic :: Scientific/Engineering :: Artificial Intelligence
Classifier: Topic :: Scientific/Engineering :: Bio-Informatics
Requires-Python: >=3.6
License-File: LICENCE.txt
Requires-Dist: h5py (>=2.2.1)
Requires-Dist: numpy (>=1.9.0)
Requires-Dist: scipy (>=1.1.0)
Requires-Dist: Cython (>=0.25.2)
Requires-Dist: mappy (>=2.16)
Requires-Dist: pysam (>=0.15)
Requires-Dist: ont-fast5-api (>=3.2)
Requires-Dist: tqdm (>=2.17)
Requires-Dist: ont-pyguppy-client-lib
Requires-Dist: scikit-learn
Requires-Dist: seaborn
Requires-Dist: ont-remora (>=1.0)
Provides-Extra: testing
Requires-Dist: pytest ; extra == 'testing'
Requires-Dist: black ; extra == 'testing'
Requires-Dist: sphinx ; extra == 'testing'
Requires-Dist: sphinx-rtd-theme ; extra == 'testing'
Requires-Dist: sphinx-argparse ; extra == 'testing'
